py_output_compare/__init__.py
py_output_compare/class_exercise.py
py_output_compare/class_topic.py
py_output_compare/compare_file.py
py_output_compare/exercise.py
py_output_compare/file_format_helper.py
py_output_compare/find_duplicate.py
py_output_compare/find_file.py
py_output_compare/get_file_run_output.py
py_output_compare/get_score.py
py_output_compare/hello.py
py_output_compare/highlight.py
py_output_compare/normalize_file_output.py
py_output_compare/problem.py
py_output_compare/test_case.py
py_output_compare/user_input_case.py
py_output_compare/datatype/__init__.py
py_output_compare/datatype/exercise.py
py_output_compare/datatype/problem.py
py_output_compare/datatype/test_case.py
py_output_compare-2.2.28.dist-info/METADATA
py_output_compare-2.2.28.dist-info/WHEEL
py_output_compare-2.2.28.dist-info/entry_points.txt
py_output_compare-2.2.28.dist-info/license
py_output_compare-2.2.28.dist-info/top_level.txt
py_output_compare-2.2.28.dist-info/RECORD
