Metadata-Version: 2.1
Name: py_output_compare
Version: 2.2.28
Summary: a script that help compare output of 2 python script, I apply this to help grading student code compare to teacher
Home-page: https://github.com/meangpu/py_output_compare
Author: meangpu
License: MIT
License-File: license
